seawater_crm/__init__.py
seawater_crm/dickson.py
seawater_crm/meta.py
seawater_crm-0.1.dist-info/LICENSE
seawater_crm-0.1.dist-info/METADATA
seawater_crm-0.1.dist-info/WHEEL
seawater_crm-0.1.dist-info/top_level.txt
seawater_crm-0.1.dist-info/RECORD
